AnimeThemes/__init__.py
AnimeThemes/__vars__.py
AnimeThemes/moe.py
AnimeThemes/types.py
animethemes-0.0.4.dist-info/METADATA
animethemes-0.0.4.dist-info/WHEEL
animethemes-0.0.4.dist-info/top_level.txt
animethemes-0.0.4.dist-info/RECORD
