Metadata-Version: 2.1
Name: animethemes
Version: 0.0.4
Summary: Unofficial https://staging.animethemes.moe Package
Home-page: https://github.com/TaprisSugarbell/AnimeThemes
Author: SayuOgiwara
Author-email: anonesayu@gmail.com
License: UNKNOWN
Project-URL: Issue tracker, https://github.com/TaprisSugarbell/AnimeThemes/issues
Platform: UNKNOWN
Requires-Dist: beautifulsoup4
Requires-Dist: cloudscraper
